catrun/__init__.py
catrun/case.py
catrun/cli.py
catrun/page.py
catrun/scaffold.py
catrun/core/__init__.py
catrun/core/android/__init__.py
catrun/core/android/driver.py
catrun/core/android/element.py
catrun/core/api/__init__.py
catrun/core/api/request.py
catrun/core/image/__init__.py
catrun/core/image/driver.py
catrun/core/image/element.py
catrun/core/ios/__init__.py
catrun/core/ios/driver.py
catrun/core/ios/element.py
catrun/core/ocr/__init__.py
catrun/core/ocr/driver.py
catrun/core/ocr/element.py
catrun/core/web/__init__.py
catrun/core/web/driver.py
catrun/core/web/element.py
catrun/running/__init__.py
catrun/running/conf.yml
catrun/running/runner.py
catrun/testdata/__init__.py
catrun/testdata/data.py
catrun/utils/__init__.py
catrun/utils/allure_util.py
catrun/utils/common.py
catrun/utils/config.py
catrun/utils/des_util.py
catrun/utils/dingtalk.py
catrun/utils/excel.py
catrun/utils/exceptions.py
catrun/utils/log.py
catrun/utils/mail.py
catrun/utils/mysql_util.py
catrun/utils/pytest_util.py
catrun/utils/swagger_util.py
demo/__init__.py
demo/run.py
demo/pages/__init__.py
demo/pages/adr_page.py
demo/pages/image_page.py
demo/pages/ios_page.py
demo/pages/ocr_page.py
demo/pages/web_page.py
demo/tests/__init__.py
demo/tests/test_adr.py
demo/tests/test_api.py
demo/tests/test_ios.py
demo/tests/test_ocr.py
demo/tests/test_web.py
kbot/__init__.py
kbot/case.py
kbot/cli.py
kbot/page.py
kbot/scaffold.py
kbot/core/__init__.py
kbot/core/android/__init__.py
kbot/core/android/driver.py
kbot/core/android/element.py
kbot/core/api/__init__.py
kbot/core/api/request.py
kbot/core/image/__init__.py
kbot/core/image/driver.py
kbot/core/image/element.py
kbot/core/ios/__init__.py
kbot/core/ios/driver.py
kbot/core/ios/element.py
kbot/core/ocr/__init__.py
kbot/core/ocr/driver.py
kbot/core/ocr/element.py
kbot/core/web/__init__.py
kbot/core/web/driver.py
kbot/core/web/element.py
kbot/running/__init__.py
kbot/running/conf.yml
kbot/running/runner.py
kbot/testdata/__init__.py
kbot/testdata/data.py
catrun-0.0.1.dist-info/METADATA
catrun-0.0.1.dist-info/WHEEL
catrun-0.0.1.dist-info/entry_points.txt
catrun-0.0.1.dist-info/top_level.txt
catrun-0.0.1.dist-info/RECORD
